MANIFEST.in
setup.py
AlienFeed.egg-info/PKG-INFO
AlienFeed.egg-info/SOURCES.txt
AlienFeed.egg-info/dependency_links.txt
AlienFeed.egg-info/entry_points.txt
AlienFeed.egg-info/requires.txt
AlienFeed.egg-info/top_level.txt
alienfeed/alien.py