Metadata-Version: 1.0
Name: AlienFeed
Version: 0.2.8
Summary: AlienFeed is a simple Reddit client for viewing and opening links from your console.
Home-page: http://github.com/jawerty/AlienFeed
Author: Jared Wright
Author-email: jawerty210@gmail.com
License: MIT
Keywords: AlienFeed alien reddit feed rss tool cli
Platform: UNKNOWN
